Metadata-Version: 2.1
Name: iocbio.fperiod
Version: 0.1.3
Summary: IOCBio FPeriod
Home-page: https://gitlab.com/iocbio/fperiod
Author: IOCBio team
Author-email: iocbio@sysbio.ioc.ee
License: BSD
Classifier: Development Status :: 4 - Beta
Classifier: Intended Audience :: Science/Research
Classifier: Programming Language :: Python :: 3
Classifier: Topic :: Scientific/Engineering
License-File: LICENSE
Requires-Dist: numpy
Requires-Dist: Cython
